<annotation>
	<folder>VOC2007</folder>
	<filename>001543.jpg</filename>
	<source>
		<database>The VOC2007 Database</database>
		<annotation>PASCAL VOC2007</annotation>
		<image>flickr</image>
		<flickrid>275248823</flickrid>
	</source>
	<owner>
		<flickrid>ppaupy</flickrid>
		<name>?</name>
	</owner>
	<size>
		<width>500</width>
		<height>375</height>
		<depth>3</depth>
	</size>
	<segmented>0</segmented>
	<object><name>tampered</name><bndbox><xmin>18</xmin><ymin>133</ymin><xmax>166</xmax><ymax>191</ymax></bndbox></object></annotation>