<annotation>
	<folder>VOC2007</folder>
	<filename>003751.jpg</filename>
	<source>
		<database>The VOC2007 Database</database>
		<annotation>PASCAL VOC2007</annotation>
		<image>flickr</image>
		<flickrid>311271015</flickrid>
	</source>
	<owner>
		<flickrid>Robb.Astro</flickrid>
		<name>Robb Meier</name>
	</owner>
	<size>
		<width>500</width>
		<height>334</height>
		<depth>3</depth>
	</size>
	<segmented>0</segmented>
	<object><name>tampered</name><bndbox><xmin>79</xmin><ymin>140</ymin><xmax>188</xmax><ymax>206</ymax></bndbox></object></annotation>