<annotation>
	<folder>VOC2007</folder>
	<filename>004655.jpg</filename>
	<source>
		<database>The VOC2007 Database</database>
		<annotation>PASCAL VOC2007</annotation>
		<image>flickr</image>
		<flickrid>339733441</flickrid>
	</source>
	<owner>
		<flickrid>GloriaUpchurch</flickrid>
		<name>Gloria Upchurch</name>
	</owner>
	<size>
		<width>500</width>
		<height>350</height>
		<depth>3</depth>
	</size>
	<segmented>0</segmented>
	<object><name>tampered</name><bndbox><xmin>274</xmin><ymin>190</ymin><xmax>464</xmax><ymax>328</ymax></bndbox></object></annotation>