<annotation>
	<folder>VOC2007</folder>
	<filename>005131.jpg</filename>
	<source>
		<database>The VOC2007 Database</database>
		<annotation>PASCAL VOC2007</annotation>
		<image>flickr</image>
		<flickrid>338065884</flickrid>
	</source>
	<owner>
		<flickrid>&amp;meg.</flickrid>
		<name>Megan</name>
	</owner>
	<size>
		<width>500</width>
		<height>375</height>
		<depth>3</depth>
	</size>
	<segmented>0</segmented>
	<object><name>tampered</name><bndbox><xmin>103</xmin><ymin>152</ymin><xmax>135</xmax><ymax>213</ymax></bndbox></object></annotation>