<annotation>
	<folder>VOC2007</folder>
	<filename>005453.jpg</filename>
	<source>
		<database>The VOC2007 Database</database>
		<annotation>PASCAL VOC2007</annotation>
		<image>flickr</image>
		<flickrid>336277124</flickrid>
	</source>
	<owner>
		<flickrid>puck90</flickrid>
		<name>?</name>
	</owner>
	<size>
		<width>500</width>
		<height>333</height>
		<depth>3</depth>
	</size>
	<segmented>0</segmented>
	<object><name>tampered</name><bndbox><xmin>20</xmin><ymin>46</ymin><xmax>35</xmax><ymax>108</ymax></bndbox></object></annotation>