<annotation>
	<folder>VOC2007</folder>
	<filename>009842.jpg</filename>
	<source>
		<database>The VOC2007 Database</database>
		<annotation>PASCAL VOC2007</annotation>
		<image>flickr</image>
		<flickrid>307593974</flickrid>
	</source>
	<owner>
		<flickrid>frankenmo's monster</flickrid>
		<name>?</name>
	</owner>
	<size>
		<width>500</width>
		<height>375</height>
		<depth>3</depth>
	</size>
	<segmented>0</segmented>
	<object><name>tampered</name><bndbox><xmin>140</xmin><ymin>54</ymin><xmax>270</xmax><ymax>287</ymax></bndbox></object></annotation>